common_utils/Readme.md
common_utils/__init__.py
common_utils/_version.py
common_utils/data_loading_management.py
common_utils/data_type_conversion.py
common_utils/date_time_methods.py
common_utils/dynamodb_methods.py
common_utils/dynamodb_ray.py
common_utils/files_methods.py
common_utils/gad_utils.py
common_utils/gad_utils_additionals.py
common_utils/json_schema_methods.py
common_utils/run_athena_query.py
common_utils/s3_methods.py
common_utils/sql_methods.py
common_utils/string_transformations.py
gad_common_utils-0.35.dist-info/METADATA
gad_common_utils-0.35.dist-info/WHEEL
gad_common_utils-0.35.dist-info/top_level.txt
gad_common_utils-0.35.dist-info/RECORD
