Metadata-Version: 2.1
Name: gad-common-utils
Version: 0.35
Summary: gad utility
Project-URL: Homepage, http://gad-co.ml
Classifier: Programming Language :: Python :: 3
Classifier: License :: OSI Approved :: MIT License
Classifier: Operating System :: OS Independent
Requires-Python: >=3.7
Requires-Dist: boto3
Requires-Dist: awswrangler
Requires-Dist: pandas
